_datalad_buildsupport/__init__.py
_datalad_buildsupport/formatters.py
_datalad_buildsupport/setup.py
datalad_metalad/__init__.py
datalad_metalad/_version.py
datalad_metalad/add.py
datalad_metalad/aggregate.py
datalad_metalad/conduct.py
datalad_metalad/dump.py
datalad_metalad/exceptions.py
datalad_metalad/extract.py
datalad_metalad/filter.py
datalad_metalad/metadatautils.py
datalad_metalad/utils.py
datalad_metalad/extractors/__init__.py
datalad_metalad/extractors/annex.py
datalad_metalad/extractors/base.py
datalad_metalad/extractors/core.py
datalad_metalad/extractors/custom.py
datalad_metalad/extractors/external.py
datalad_metalad/extractors/external_dataset.py
datalad_metalad/extractors/external_file.py
datalad_metalad/extractors/genericjson_dataset.py
datalad_metalad/extractors/genericjson_file.py
datalad_metalad/extractors/metalad_example_dataset.py
datalad_metalad/extractors/metalad_example_file.py
datalad_metalad/extractors/runprov.py
datalad_metalad/extractors/legacy/__init__.py
datalad_metalad/extractors/legacy/annex.py
datalad_metalad/extractors/legacy/audio.py
datalad_metalad/extractors/legacy/datacite.py
datalad_metalad/extractors/legacy/datalad_core.py
datalad_metalad/extractors/legacy/datalad_rfc822.py
datalad_metalad/extractors/legacy/definitions.py
datalad_metalad/extractors/legacy/exif.py
datalad_metalad/extractors/legacy/frictionless_datapackage.py
datalad_metalad/extractors/legacy/image.py
datalad_metalad/extractors/legacy/xmp.py
datalad_metalad/extractors/legacy/tests/__init__.py
datalad_metalad/extractors/legacy/tests/test_audio.py
datalad_metalad/extractors/legacy/tests/test_base.py
datalad_metalad/extractors/legacy/tests/test_datacite_xml.py
datalad_metalad/extractors/legacy/tests/test_exif.py
datalad_metalad/extractors/legacy/tests/test_frictionless_datapackage.py
datalad_metalad/extractors/legacy/tests/test_image.py
datalad_metalad/extractors/legacy/tests/test_rfc822.py
datalad_metalad/extractors/legacy/tests/test_xmp.py
datalad_metalad-0.14.20.dist-info/COPYING
datalad_metalad-0.14.20.dist-info/METADATA
datalad_metalad-0.14.20.dist-info/WHEEL
datalad_metalad-0.14.20.dist-info/entry_points.txt
datalad_metalad-0.14.20.dist-info/top_level.txt
datalad_metalad-0.14.20.dist-info/RECORD
