Metadata-Version: 2.1
Name: datalad_metalad
Version: 0.14.20
Summary: DataLad extension for semantic metadata handling
Home-page: https://github.com/datalad/datalad-metalad
Author: The DataLad Team and Contributors
Author-email: team@datalad.org
License: MIT
Classifier: Programming Language :: Python
Classifier: License :: OSI Approved :: BSD License
Classifier: Programming Language :: Python :: 3
Requires-Python: >=3.7
License-File: COPYING
Requires-Dist: datalad >=0.18
Requires-Dist: datalad-metadata-model >=0.3.10
Requires-Dist: datalad-deprecated
Requires-Dist: pytest
Requires-Dist: pyyaml
